{
  "delta_id": "delta_cp_1780445214.618021",
  "base_id": "cp_1780445191.2398303",
  "sequence_no": 3,
  "created_at": 1780445214.618021,
  "cycle_count": 400,
  "base_cycle_count": 100,
  "trace_offset": 300,
  "new_traces": [
    {
      "event_id": "7eafff61-b9bf-49bf-915d-f0a0dd9a2a63",
      "session_id": "cap_workload",
      "sequence_no": 1,
      "correlation_id": "5bd052d9-fbe1-4aec-a475-8e57acee027c",
      "preflight_valid": true,
      "preflight_reason": "preflight_passed",
      "preflight_rules_triggered": [],
      "risk_score": 0.1,
      "p4_verdict": "ALLOW",
      "p4_reason": "risk_within_threshold",
      "p4_risk_level": "low",
      "p4_rule_triggered": null,
      "execution_status": "SUCCESS",
      "execution_error": null,
      "capabilities_checked": [
        "filesystem.read"
      ],
      "resource_usage": {},
      "preflight_time": 0.0,
      "p4_time": 0.0,
      "execution_time": 0.00799703598022461,
      "total_time": 0.0,
      "final_status": "P4_ALLOW"
    },
    {
      "event_id": "08024b64-2a8f-4b2f-a517-389943e7eb6c",
      "session_id": "cap_workload",
      "sequence_no": 1,
      "correlation_id": "ebffbb53-0411-41bf-b095-6fa74794d90e",
      "preflight_valid": true,
      "preflight_reason": "preflight_passed",
      "preflight_rules_triggered": [],
      "risk_score": 0.1,
      "p4_verdict": "ALLOW",
      "p4_reason": "risk_within_threshold",
      "p4_risk_level": "low",
      "p4_rule_triggered": null,
      "execution_status": "SUCCESS",
      "execution_error": null,
      "capabilities_checked": [
        "filesystem.read"
      ],
      "resource_usage": {},
      "preflight_time": 0.0,
      "p4_time": 0.0,
      "execution_time": 0.0,
      "total_time": 0.0,
      "final_status": "P4_ALLOW"
    },
    {
      "event_id": "2da4fbd6-6404-44b3-a291-3b1be684c948",
      "session_id": "cap_workload",
      "sequence_no": 1,
      "correlation_id": "eda1e356-ff53-416c-b6cf-4dcb756c182f",
      "preflight_valid": true,
      "preflight_reason": "preflight_passed",
      "preflight_rules_triggered": [],
      "risk_score": 0.1,
      "p4_verdict": "ALLOW",
      "p4_reason": "risk_within_threshold",
      "p4_risk_level": "low",
      "p4_rule_triggered": null,
      "execution_status": "SUCCESS",
      "execution_error": null,
      "capabilities_checked": [
        "filesystem.read"
      ],
      "resource_usage": {},
      "preflight_time": 0.0,
      "p4_time": 0.0,
      "execution_time": 0.0009922981262207031,
      "total_time": 0.0,
      "final_status": "P4_ALLOW"
    },
    {
      "event_id": "2cf5fc08-e124-4bb9-ab28-73748d2cf200",
      "session_id": "cap_workload",
      "sequence_no": 1,
      "correlation_id": "e5596657-4c31-4fe3-a2fe-09efc7dcddae",
      "preflight_valid": true,
      "preflight_reason": "preflight_passed",
      "preflight_rules_triggered": [],
      "risk_score": 0.1,
      "p4_verdict": "ALLOW",
      "p4_reason": "risk_within_threshold",
      "p4_risk_level": "low",
      "p4_rule_triggered": null,
      "execution_status": "SUCCESS",
      "execution_error": null,
      "capabilities_checked": [
        "filesystem.read"
      ],
      "resource_usage": {},
      "preflight_time": 0.0,
      "p4_time": 0.0,
      "execution_time": 0.0075228214263916016,
      "total_time": 0.0,
      "final_status": "P4_ALLOW"
    },
    {
      "event_id": "81045567-3430-49a2-8c09-1e716d7969d1",
      "session_id": "cap_workload",
      "sequence_no": 1,
      "correlation_id": "0c86f493-c78f-4ea1-844b-796da50a8b52",
      "preflight_valid": true,
      "preflight_reason": "preflight_passed",
      "preflight_rules_triggered": [],
      "risk_score": 0.1,
      "p4_verdict": "ALLOW",
      "p4_reason": "risk_within_threshold",
      "p4_risk_level": "low",
      "p4_rule_triggered": null,
      "execution_status": "SUCCESS",
      "execution_error": null,
      "capabilities_checked": [
        "filesystem.read"
      ],
      "resource_usage": {},
      "preflight_time": 0.0,
      "p4_time": 0.0,
      "execution_time": 0.21608567237854004,
      "total_time": 0.0,
      "final_status": "P4_ALLOW"
    },
    {
      "event_id": "478506f6-1c04-441f-b6ea-b5db6ee41bbc",
      "session_id": "cap_workload",
      "sequence_no": 1,
      "correlation_id": "a3ae6d90-dc3d-4b6b-a8ea-e00879180a10",
      "preflight_valid": true,
      "preflight_reason": "preflight_passed",
      "preflight_rules_triggered": [],
      "risk_score": 0.1,
      "p4_verdict": "ALLOW",
      "p4_reason": "risk_within_threshold",
      "p4_risk_level": "low",
      "p4_rule_triggered": null,
      "execution_status": "SUCCESS",
      "execution_error": null,
      "capabilities_checked": [
        "filesystem.read"
      ],
      "resource_usage": {},
      "preflight_time": 0.0,
      "p4_time": 0.0,
      "execution_time": 0.0029637813568115234,
      "total_time": 0.0,
      "final_status": "P4_ALLOW"
    },
    {
      "event_id": "ec90e5a1-bd21-452c-a240-bd2e5bfe1683",
      "session_id": "cap_workload",
      "sequence_no": 1,
      "correlation_id": "28fffbc4-6430-4ac7-8100-fa886f160759",
      "preflight_valid": true,
      "preflight_reason": "preflight_passed",
      "preflight_rules_triggered": [],
      "risk_score": 0.1,
      "p4_verdict": "ALLOW",
      "p4_reason": "risk_within_threshold",
      "p4_risk_level": "low",
      "p4_rule_triggered": null,
      "execution_status": "SUCCESS",
      "execution_error": null,
      "capabilities_checked": [
        "filesystem.read"
      ],
      "resource_usage": {},
      "preflight_time": 0.0,
      "p4_time": 0.0,
      "execution_time": 0.0009982585906982422,
      "total_time": 0.0,
      "final_status": "P4_ALLOW"
    },
    {
      "event_id": "e2e132c6-c8ee-4e30-a9fd-8f7951c71885",
      "session_id": "cap_workload",
      "sequence_no": 1,
      "correlation_id": "e9789510-7c69-40f7-8814-2ef1a1fd81a4",
      "preflight_valid": true,
      "preflight_reason": "preflight_passed",
      "preflight_rules_triggered": [],
      "risk_score": 0.1,
      "p4_verdict": "ALLOW",
      "p4_reason": "risk_within_threshold",
      "p4_risk_level": "low",
      "p4_rule_triggered": null,
      "execution_status": "SUCCESS",
      "execution_error": null,
      "capabilities_checked": [
        "filesystem.read"
      ],
      "resource_usage": {},
      "preflight_time": 0.0,
      "p4_time": 0.0,
      "execution_time": 0.00799870491027832,
      "total_time": 0.0,
      "final_status": "P4_ALLOW"
    },
    {
      "event_id": "3e7aa8e9-c076-4291-98ee-73e7d5265a17",
      "session_id": "cap_workload",
      "sequence_no": 1,
      "correlation_id": "4f9d3371-5d2c-4d7a-bb06-967c13f62b55",
      "preflight_valid": true,
      "preflight_reason": "preflight_passed",
      "preflight_rules_triggered": [],
      "risk_score": 0.1,
      "p4_verdict": "ALLOW",
      "p4_reason": "risk_within_threshold",
      "p4_risk_level": "low",
      "p4_rule_triggered": null,
      "execution_status": "SUCCESS",
      "execution_error": null,
      "capabilities_checked": [
        "filesystem.read"
      ],
      "resource_usage": {},
      "preflight_time": 0.0,
      "p4_time": 0.0,
      "execution_time": 0.010001659393310547,
      "total_time": 0.0,
      "final_status": "P4_ALLOW"
    },
    {
      "event_id": "da7a511f-17e4-44cc-a171-ba6d8dd90967",
      "session_id": "cap_workload",
      "sequence_no": 1,
      "correlation_id": "ba990411-b097-40ed-8e0f-6a6590185a21",
      "preflight_valid": true,
      "preflight_reason": "preflight_passed",
      "preflight_rules_triggered": [],
      "risk_score": 0.1,
      "p4_verdict": "ALLOW",
      "p4_reason": "risk_within_threshold",
      "p4_risk_level": "low",
      "p4_rule_triggered": null,
      "execution_status": "SUCCESS",
      "execution_error": null,
      "capabilities_checked": [
        "filesystem.read"
      ],
      "resource_usage": {},
      "preflight_time": 0.0,
      "p4_time": 0.0,
      "execution_time": 0.14256548881530762,
      "total_time": 0.0,
      "final_status": "P4_ALLOW"
    },
    {
      "event_id": "8a22eac3-178f-4394-a90d-6dc5fdd1afc0",
      "session_id": "cap_workload",
      "sequence_no": 1,
      "correlation_id": "218f9c2d-dd80-485a-8a15-bd2270cb711d",
      "preflight_valid": true,
      "preflight_reason": "preflight_passed",
      "preflight_rules_triggered": [],
      "risk_score": 0.1,
      "p4_verdict": "ALLOW",
      "p4_reason": "risk_within_threshold",
      "p4_risk_level": "low",
      "p4_rule_triggered": null,
      "execution_status": "SUCCESS",
      "execution_error": null,
      "capabilities_checked": [
        "filesystem.read"
      ],
      "resource_usage": {},
      "preflight_time": 0.0,
      "p4_time": 0.0,
      "execution_time": 0.0030002593994140625,
      "total_time": 0.0,
      "final_status": "P4_ALLOW"
    },
    {
      "event_id": "19c7dac1-3bdc-498b-8a84-7b9a1feca124",
      "session_id": "cap_workload",
      "sequence_no": 1,
      "correlation_id": "727bf840-19ca-4e59-8de8-38e72421e266",
      "preflight_valid": true,
      "preflight_reason": "preflight_passed",
      "preflight_rules_triggered": [],
      "risk_score": 0.1,
      "p4_verdict": "ALLOW",
      "p4_reason": "risk_within_threshold",
      "p4_risk_level": "low",
      "p4_rule_triggered": null,
      "execution_status": "SUCCESS",
      "execution_error": null,
      "capabilities_checked": [
        "filesystem.read"
      ],
      "resource_usage": {},
      "preflight_time": 0.0,
      "p4_time": 0.0,
      "execution_time": 0.0010013580322265625,
      "total_time": 0.0,
      "final_status": "P4_ALLOW"
    },
    {
      "event_id": "0830379f-78ad-47e7-84d1-1dc2b42d6ff3",
      "session_id": "cap_workload",
      "sequence_no": 1,
      "correlation_id": "2eb8dcbc-021a-482a-bd15-fbf589498608",
      "preflight_valid": true,
      "preflight_reason": "preflight_passed",
      "preflight_rules_triggered": [],
      "risk_score": 0.1,
      "p4_verdict": "ALLOW",
      "p4_reason": "risk_within_threshold",
      "p4_risk_level": "low",
      "p4_rule_triggered": null,
      "execution_status": "SUCCESS",
      "execution_error": null,
      "capabilities_checked": [
        "filesystem.read"
      ],
      "resource_usage": {},
      "preflight_time": 0.0,
      "p4_time": 0.0,
      "execution_time": 0.0010025501251220703,
      "total_time": 0.0,
      "final_status": "P4_ALLOW"
    },
    {
      "event_id": "ba1841a7-1721-4cd5-9bac-64bb7d31aeda",
      "session_id": "cap_workload",
      "sequence_no": 1,
      "correlation_id": "771eb9db-b688-46a7-a0ac-73df073022fa",
      "preflight_valid": true,
      "preflight_reason": "preflight_passed",
      "preflight_rules_triggered": [],
      "risk_score": 0.1,
      "p4_verdict": "ALLOW",
      "p4_reason": "risk_within_threshold",
      "p4_risk_level": "low",
      "p4_rule_triggered": null,
      "execution_status": "SUCCESS",
      "execution_error": null,
      "capabilities_checked": [
        "filesystem.read"
      ],
      "resource_usage": {},
      "preflight_time": 0.0,
      "p4_time": 0.0,
      "execution_time": 0.024024009704589844,
      "total_time": 0.0,
      "final_status": "P4_ALLOW"
    },
    {
      "event_id": "055acbf5-0309-4e32-979b-be040aef4c30",
      "session_id": "cap_workload",
      "sequence_no": 1,
      "correlation_id": "936cfda7-b33a-468f-8477-cf63c2282217",
      "preflight_valid": true,
      "preflight_reason": "preflight_passed",
      "preflight_rules_triggered": [],
      "risk_score": 0.1,
      "p4_verdict": "ALLOW",
      "p4_reason": "risk_within_threshold",
      "p4_risk_level": "low",
      "p4_rule_triggered": null,
      "execution_status": "SUCCESS",
      "execution_error": null,
      "capabilities_checked": [
        "filesystem.read"
      ],
      "resource_usage": {},
      "preflight_time": 0.0,
      "p4_time": 0.0,
      "execution_time": 0.1220848560333252,
      "total_time": 0.0,
      "final_status": "P4_ALLOW"
    },
    {
      "event_id": "33e69e41-ffab-4b8a-adcb-bcadf2f2f4f9",
      "session_id": "cap_workload",
      "sequence_no": 1,
      "correlation_id": "9c8d2b60-97ba-4193-aa5e-d89cb82b0304",
      "preflight_valid": true,
      "preflight_reason": "preflight_passed",
      "preflight_rules_triggered": [],
      "risk_score": 0.1,
      "p4_verdict": "ALLOW",
      "p4_reason": "risk_within_threshold",
      "p4_risk_level": "low",
      "p4_rule_triggered": null,
      "execution_status": "SUCCESS",
      "execution_error": null,
      "capabilities_checked": [
        "filesystem.read"
      ],
      "resource_usage": {},
      "preflight_time": 0.0,
      "p4_time": 0.0,
      "execution_time": 0.00999760627746582,
      "total_time": 0.0,
      "final_status": "P4_ALLOW"
    },
    {
      "event_id": "55c4a6df-636f-415f-bd22-8522ac22540d",
      "session_id": "cap_workload",
      "sequence_no": 1,
      "correlation_id": "82494f66-fc23-42fb-96cc-3013a77b30c6",
      "preflight_valid": true,
      "preflight_reason": "preflight_passed",
      "preflight_rules_triggered": [],
      "risk_score": 0.1,
      "p4_verdict": "ALLOW",
      "p4_reason": "risk_within_threshold",
      "p4_risk_level": "low",
      "p4_rule_triggered": null,
      "execution_status": "SUCCESS",
      "execution_error": null,
      "capabilities_checked": [
        "filesystem.read"
      ],
      "resource_usage": {},
      "preflight_time": 0.0,
      "p4_time": 0.0,
      "execution_time": 0.0010077953338623047,
      "total_time": 0.0,
      "final_status": "P4_ALLOW"
    },
    {
      "event_id": "b3e1777b-ec47-4f27-b9c5-70b8a9faa6b2",
      "session_id": "cap_workload",
      "sequence_no": 1,
      "correlation_id": "9a7154bc-3c2e-4791-9293-456bdaa629a3",
      "preflight_valid": true,
      "preflight_reason": "preflight_passed",
      "preflight_rules_triggered": [],
      "risk_score": 0.1,
      "p4_verdict": "ALLOW",
      "p4_reason": "risk_within_threshold",
      "p4_risk_level": "low",
      "p4_rule_triggered": null,
      "execution_status": "SUCCESS",
      "execution_error": null,
      "capabilities_checked": [
        "filesystem.read"
      ],
      "resource_usage": {},
      "preflight_time": 0.0,
      "p4_time": 0.0,
      "execution_time": 0.0030078887939453125,
      "total_time": 0.0,
      "final_status": "P4_ALLOW"
    },
    {
      "event_id": "8259c6b7-13a3-43df-940d-02abdfe36b45",
      "session_id": "cap_workload",
      "sequence_no": 1,
      "correlation_id": "e553cb57-5c18-43a0-9ce0-70d519cc5de0",
      "preflight_valid": true,
      "preflight_reason": "preflight_passed",
      "preflight_rules_triggered": [],
      "risk_score": 0.1,
      "p4_verdict": "ALLOW",
      "p4_reason": "risk_within_threshold",
      "p4_risk_level": "low",
      "p4_rule_triggered": null,
      "execution_status": "SUCCESS",
      "execution_error": null,
      "capabilities_checked": [
        "filesystem.read"
      ],
      "resource_usage": {},
      "preflight_time": 0.0,
      "p4_time": 0.0,
      "execution_time": 0.01900172233581543,
      "total_time": 0.0,
      "final_status": "P4_ALLOW"
    },
    {
      "event_id": "128a2549-026d-4c44-9adc-3e12fea2a1df",
      "session_id": "cap_workload",
      "sequence_no": 1,
      "correlation_id": "66c5c05d-a53a-4cfc-acc7-3abfc258cde4",
      "preflight_valid": true,
      "preflight_reason": "preflight_passed",
      "preflight_rules_triggered": [],
      "risk_score": 0.1,
      "p4_verdict": "ALLOW",
      "p4_reason": "risk_within_threshold",
      "p4_risk_level": "low",
      "p4_rule_triggered": null,
      "execution_status": "SUCCESS",
      "execution_error": null,
      "capabilities_checked": [
        "filesystem.read"
      ],
      "resource_usage": {},
      "preflight_time": 0.0,
      "p4_time": 0.0,
      "execution_time": 0.15908098220825195,
      "total_time": 0.0,
      "final_status": "P4_ALLOW"
    },
    {
      "event_id": "701d63ac-b455-4cd3-a341-6bbf9be2fd4c",
      "session_id": "cap_workload",
      "sequence_no": 1,
      "correlation_id": "c8be2fa0-2ee0-4098-ad35-460a93e00543",
      "preflight_valid": true,
      "preflight_reason": "preflight_passed",
      "preflight_rules_triggered": [],
      "risk_score": 0.1,
      "p4_verdict": "ALLOW",
      "p4_reason": "risk_within_threshold",
      "p4_risk_level": "low",
      "p4_rule_triggered": null,
      "execution_status": "SUCCESS",
      "execution_error": null,
      "capabilities_checked": [
        "filesystem.read"
      ],
      "resource_usage": {},
      "preflight_time": 0.0,
      "p4_time": 0.0,
      "execution_time": 0.00699615478515625,
      "total_time": 0.0,
      "final_status": "P4_ALLOW"
    },
    {
      "event_id": "5f45853f-0dde-4966-ae41-fa3390c24d79",
      "session_id": "cap_workload",
      "sequence_no": 1,
      "correlation_id": "241ec6fd-85fd-45ca-964f-c65bfbf86e6e",
      "preflight_valid": true,
      "preflight_reason": "preflight_passed",
      "preflight_rules_triggered": [],
      "risk_score": 0.1,
      "p4_verdict": "ALLOW",
      "p4_reason": "risk_within_threshold",
      "p4_risk_level": "low",
      "p4_rule_triggered": null,
      "execution_status": "SUCCESS",
      "execution_error": null,
      "capabilities_checked": [
        "filesystem.read"
      ],
      "resource_usage": {},
      "preflight_time": 0.0,
      "p4_time": 0.0,
      "execution_time": 0.0,
      "total_time": 0.0,
      "final_status": "P4_ALLOW"
    },
    {
      "event_id": "2075cba2-0772-49d0-a28e-cc90b3fb4e95",
      "session_id": "cap_workload",
      "sequence_no": 1,
      "correlation_id": "8838cbc7-0919-4939-8911-b594d3af91d3",
      "preflight_valid": true,
      "preflight_reason": "preflight_passed",
      "preflight_rules_triggered": [],
      "risk_score": 0.1,
      "p4_verdict": "ALLOW",
      "p4_reason": "risk_within_threshold",
      "p4_risk_level": "low",
      "p4_rule_triggered": null,
      "execution_status": "SUCCESS",
      "execution_error": null,
      "capabilities_checked": [
        "filesystem.read"
      ],
      "resource_usage": {},
      "preflight_time": 0.0,
      "p4_time": 0.0,
      "execution_time": 0.0009992122650146484,
      "total_time": 0.0,
      "final_status": "P4_ALLOW"
    },
    {
      "event_id": "038d9bb3-b142-4408-8e7a-12b78240f8f7",
      "session_id": "cap_workload",
      "sequence_no": 1,
      "correlation_id": "d1a746c2-09d9-4612-81f3-a9bbb39f2b41",
      "preflight_valid": true,
      "preflight_reason": "preflight_passed",
      "preflight_rules_triggered": [],
      "risk_score": 0.1,
      "p4_verdict": "ALLOW",
      "p4_reason": "risk_within_threshold",
      "p4_risk_level": "low",
      "p4_rule_triggered": null,
      "execution_status": "SUCCESS",
      "execution_error": null,
      "capabilities_checked": [
        "filesystem.read"
      ],
      "resource_usage": {},
      "preflight_time": 0.0,
      "p4_time": 0.0,
      "execution_time": 0.012001276016235352,
      "total_time": 0.0,
      "final_status": "P4_ALLOW"
    },
    {
      "event_id": "a1f902d1-f86a-4612-878c-99174dd530dc",
      "session_id": "cap_workload",
      "sequence_no": 1,
      "correlation_id": "087a0040-3d41-4d64-a614-3f95b84dc91a",
      "preflight_valid": true,
      "preflight_reason": "preflight_passed",
      "preflight_rules_triggered": [],
      "risk_score": 0.1,
      "p4_verdict": "ALLOW",
      "p4_reason": "risk_within_threshold",
      "p4_risk_level": "low",
      "p4_rule_triggered": null,
      "execution_status": "SUCCESS",
      "execution_error": null,
      "capabilities_checked": [
        "filesystem.read"
      ],
      "resource_usage": {},
      "preflight_time": 0.0,
      "p4_time": 0.0,
      "execution_time": 0.146073579788208,
      "total_time": 0.0,
      "final_status": "P4_ALLOW"
    },
    {
      "event_id": "53dbe425-3bf7-4c2b-b148-34bb1005c1f3",
      "session_id": "cap_workload",
      "sequence_no": 1,
      "correlation_id": "d3803e12-a75e-4e75-b928-4a3b1471b765",
      "preflight_valid": true,
      "preflight_reason": "preflight_passed",
      "preflight_rules_triggered": [],
      "risk_score": 0.1,
      "p4_verdict": "ALLOW",
      "p4_reason": "risk_within_threshold",
      "p4_risk_level": "low",
      "p4_rule_triggered": null,
      "execution_status": "SUCCESS",
      "execution_error": null,
      "capabilities_checked": [
        "filesystem.read"
      ],
      "resource_usage": {},
      "preflight_time": 0.0,
      "p4_time": 0.0,
      "execution_time": 0.0029993057250976562,
      "total_time": 0.0,
      "final_status": "P4_ALLOW"
    },
    {
      "event_id": "cc2c1ecc-d623-4294-9bd9-4a53f165653d",
      "session_id": "cap_workload",
      "sequence_no": 1,
      "correlation_id": "46922c72-d162-448c-9588-cf0ffb9331bc",
      "preflight_valid": true,
      "preflight_reason": "preflight_passed",
      "preflight_rules_triggered": [],
      "risk_score": 0.1,
      "p4_verdict": "ALLOW",
      "p4_reason": "risk_within_threshold",
      "p4_risk_level": "low",
      "p4_rule_triggered": null,
      "execution_status": "SUCCESS",
      "execution_error": null,
      "capabilities_checked": [
        "filesystem.read"
      ],
      "resource_usage": {},
      "preflight_time": 0.0,
      "p4_time": 0.0,
      "execution_time": 0.0,
      "total_time": 0.0,
      "final_status": "P4_ALLOW"
    },
    {
      "event_id": "b5d7e747-8995-4de4-800a-a29df6459f67",
      "session_id": "cap_workload",
      "sequence_no": 1,
      "correlation_id": "e4d51eb4-8d18-4df5-b742-ace5ad62f868",
      "preflight_valid": true,
      "preflight_reason": "preflight_passed",
      "preflight_rules_triggered": [],
      "risk_score": 0.1,
      "p4_verdict": "ALLOW",
      "p4_reason": "risk_within_threshold",
      "p4_risk_level": "low",
      "p4_rule_triggered": null,
      "execution_status": "SUCCESS",
      "execution_error": null,
      "capabilities_checked": [
        "filesystem.read"
      ],
      "resource_usage": {},
      "preflight_time": 0.0,
      "p4_time": 0.0,
      "execution_time": 0.0010020732879638672,
      "total_time": 0.0,
      "final_status": "P4_ALLOW"
    },
    {
      "event_id": "a566d6fe-b0df-43d6-b1b1-19e0e16e9986",
      "session_id": "cap_workload",
      "sequence_no": 1,
      "correlation_id": "a91c50df-ffd3-4a00-a29c-4f4919879f4f",
      "preflight_valid": true,
      "preflight_reason": "preflight_passed",
      "preflight_rules_triggered": [],
      "risk_score": 0.1,
      "p4_verdict": "ALLOW",
      "p4_reason": "risk_within_threshold",
      "p4_risk_level": "low",
      "p4_rule_triggered": null,
      "execution_status": "SUCCESS",
      "execution_error": null,
      "capabilities_checked": [
        "filesystem.read"
      ],
      "resource_usage": {},
      "preflight_time": 0.0,
      "p4_time": 0.0,
      "execution_time": 0.015005111694335938,
      "total_time": 0.0,
      "final_status": "P4_ALLOW"
    },
    {
      "event_id": "8ab66d09-8408-4042-a8e5-d2961a2897a8",
      "session_id": "cap_workload",
      "sequence_no": 1,
      "correlation_id": "b438148c-b687-4147-b103-a71adc962bf9",
      "preflight_valid": true,
      "preflight_reason": "preflight_passed",
      "preflight_rules_triggered": [],
      "risk_score": 0.1,
      "p4_verdict": "ALLOW",
      "p4_reason": "risk_within_threshold",
      "p4_risk_level": "low",
      "p4_rule_triggered": null,
      "execution_status": "SUCCESS",
      "execution_error": null,
      "capabilities_checked": [
        "filesystem.read"
      ],
      "resource_usage": {},
      "preflight_time": 0.0,
      "p4_time": 0.0,
      "execution_time": 0.15107941627502441,
      "total_time": 0.0,
      "final_status": "P4_ALLOW"
    },
    {
      "event_id": "38fc0821-aeae-4078-9028-93feb459a548",
      "session_id": "cap_workload",
      "sequence_no": 1,
      "correlation_id": "c695b974-04f7-4674-be2a-41789159bf2a",
      "preflight_valid": true,
      "preflight_reason": "preflight_passed",
      "preflight_rules_triggered": [],
      "risk_score": 0.1,
      "p4_verdict": "ALLOW",
      "p4_reason": "risk_within_threshold",
      "p4_risk_level": "low",
      "p4_rule_triggered": null,
      "execution_status": "SUCCESS",
      "execution_error": null,
      "capabilities_checked": [
        "filesystem.read"
      ],
      "resource_usage": {},
      "preflight_time": 0.0,
      "p4_time": 0.0,
      "execution_time": 0.004000425338745117,
      "total_time": 0.0,
      "final_status": "P4_ALLOW"
    },
    {
      "event_id": "f2d928cb-9de4-426a-b7d5-b6368d67a32f",
      "session_id": "cap_workload",
      "sequence_no": 1,
      "correlation_id": "92465595-3a37-4202-ae6e-31b2a238965d",
      "preflight_valid": true,
      "preflight_reason": "preflight_passed",
      "preflight_rules_triggered": [],
      "risk_score": 0.1,
      "p4_verdict": "ALLOW",
      "p4_reason": "risk_within_threshold",
      "p4_risk_level": "low",
      "p4_rule_triggered": null,
      "execution_status": "SUCCESS",
      "execution_error": null,
      "capabilities_checked": [
        "filesystem.read"
      ],
      "resource_usage": {},
      "preflight_time": 0.0,
      "p4_time": 0.0,
      "execution_time": 0.000993967056274414,
      "total_time": 0.0,
      "final_status": "P4_ALLOW"
    },
    {
      "event_id": "51453236-74cd-4323-84c3-91f1e7b22d9b",
      "session_id": "cap_workload",
      "sequence_no": 1,
      "correlation_id": "84176476-1c8d-4f0c-8060-3f823414d752",
      "preflight_valid": true,
      "preflight_reason": "preflight_passed",
      "preflight_rules_triggered": [],
      "risk_score": 0.1,
      "p4_verdict": "ALLOW",
      "p4_reason": "risk_within_threshold",
      "p4_risk_level": "low",
      "p4_rule_triggered": null,
      "execution_status": "SUCCESS",
      "execution_error": null,
      "capabilities_checked": [
        "filesystem.read"
      ],
      "resource_usage": {},
      "preflight_time": 0.0,
      "p4_time": 0.0,
      "execution_time": 0.0010004043579101562,
      "total_time": 0.0,
      "final_status": "P4_ALLOW"
    },
    {
      "event_id": "e73a71ba-4cdc-463e-8959-f46686574cb6",
      "session_id": "cap_workload",
      "sequence_no": 1,
      "correlation_id": "2249573a-c7c6-44f6-bf47-a23fd67b7bf6",
      "preflight_valid": true,
      "preflight_reason": "preflight_passed",
      "preflight_rules_triggered": [],
      "risk_score": 0.1,
      "p4_verdict": "ALLOW",
      "p4_reason": "risk_within_threshold",
      "p4_risk_level": "low",
      "p4_rule_triggered": null,
      "execution_status": "SUCCESS",
      "execution_error": null,
      "capabilities_checked": [
        "filesystem.read"
      ],
      "resource_usage": {},
      "preflight_time": 0.0,
      "p4_time": 0.0,
      "execution_time": 0.01599717140197754,
      "total_time": 0.0,
      "final_status": "P4_ALLOW"
    },
    {
      "event_id": "3dd69b64-5c1e-40de-98be-e1d2356ebe50",
      "session_id": "cap_workload",
      "sequence_no": 1,
      "correlation_id": "b76066a8-33eb-45d9-8631-15f1ddeffbab",
      "preflight_valid": true,
      "preflight_reason": "preflight_passed",
      "preflight_rules_triggered": [],
      "risk_score": 0.1,
      "p4_verdict": "ALLOW",
      "p4_reason": "risk_within_threshold",
      "p4_risk_level": "low",
      "p4_rule_triggered": null,
      "execution_status": "SUCCESS",
      "execution_error": null,
      "capabilities_checked": [
        "filesystem.read"
      ],
      "resource_usage": {},
      "preflight_time": 0.0,
      "p4_time": 0.0,
      "execution_time": 0.1365516185760498,
      "total_time": 0.0,
      "final_status": "P4_ALLOW"
    },
    {
      "event_id": "3162ca2f-476f-4872-b435-c30e5fe4c998",
      "session_id": "cap_workload",
      "sequence_no": 1,
      "correlation_id": "fc043094-7062-409d-84e5-685e0a08d987",
      "preflight_valid": true,
      "preflight_reason": "preflight_passed",
      "preflight_rules_triggered": [],
      "risk_score": 0.1,
      "p4_verdict": "ALLOW",
      "p4_reason": "risk_within_threshold",
      "p4_risk_level": "low",
      "p4_rule_triggered": null,
      "execution_status": "SUCCESS",
      "execution_error": null,
      "capabilities_checked": [
        "filesystem.read"
      ],
      "resource_usage": {},
      "preflight_time": 0.0,
      "p4_time": 0.0,
      "execution_time": 0.009018659591674805,
      "total_time": 0.0,
      "final_status": "P4_ALLOW"
    },
    {
      "event_id": "b8bca47f-548d-4331-8cd3-d1c147b676ca",
      "session_id": "cap_workload",
      "sequence_no": 1,
      "correlation_id": "08c5465d-6127-4f3f-84c5-170156ea181b",
      "preflight_valid": true,
      "preflight_reason": "preflight_passed",
      "preflight_rules_triggered": [],
      "risk_score": 0.1,
      "p4_verdict": "ALLOW",
      "p4_reason": "risk_within_threshold",
      "p4_risk_level": "low",
      "p4_rule_triggered": null,
      "execution_status": "SUCCESS",
      "execution_error": null,
      "capabilities_checked": [
        "filesystem.read"
      ],
      "resource_usage": {},
      "preflight_time": 0.0,
      "p4_time": 0.0,
      "execution_time": 0.0,
      "total_time": 0.0,
      "final_status": "P4_ALLOW"
    },
    {
      "event_id": "d4d2d558-c8cb-4a5c-976e-f8b8aa8520d2",
      "session_id": "cap_workload",
      "sequence_no": 1,
      "correlation_id": "9cc19668-b61b-4215-a3ac-d410ade622bb",
      "preflight_valid": true,
      "preflight_reason": "preflight_passed",
      "preflight_rules_triggered": [],
      "risk_score": 0.1,
      "p4_verdict": "ALLOW",
      "p4_reason": "risk_within_threshold",
      "p4_risk_level": "low",
      "p4_rule_triggered": null,
      "execution_status": "SUCCESS",
      "execution_error": null,
      "capabilities_checked": [
        "filesystem.read"
      ],
      "resource_usage": {},
      "preflight_time": 0.0,
      "p4_time": 0.0,
      "execution_time": 0.0,
      "total_time": 0.0,
      "final_status": "P4_ALLOW"
    },
    {
      "event_id": "69913432-fa35-4b73-a417-8b2f392ce1c1",
      "session_id": "cap_workload",
      "sequence_no": 1,
      "correlation_id": "b1c8eb3f-031a-41c9-b6f9-ddf41cd754fd",
      "preflight_valid": true,
      "preflight_reason": "preflight_passed",
      "preflight_rules_triggered": [],
      "risk_score": 0.1,
      "p4_verdict": "ALLOW",
      "p4_reason": "risk_within_threshold",
      "p4_risk_level": "low",
      "p4_rule_triggered": null,
      "execution_status": "SUCCESS",
      "execution_error": null,
      "capabilities_checked": [
        "filesystem.read"
      ],
      "resource_usage": {},
      "preflight_time": 0.0010039806365966797,
      "p4_time": 0.0010039806365966797,
      "execution_time": 0.015001773834228516,
      "total_time": 0.0010039806365966797,
      "final_status": "P4_ALLOW"
    },
    {
      "event_id": "e3a25a17-d17b-466c-a7b1-f61fd58b7a64",
      "session_id": "cap_workload",
      "sequence_no": 1,
      "correlation_id": "d9ccd000-448e-422b-b5da-df340cce878d",
      "preflight_valid": true,
      "preflight_reason": "preflight_passed",
      "preflight_rules_triggered": [],
      "risk_score": 0.1,
      "p4_verdict": "ALLOW",
      "p4_reason": "risk_within_threshold",
      "p4_risk_level": "low",
      "p4_rule_triggered": null,
      "execution_status": "SUCCESS",
      "execution_error": null,
      "capabilities_checked": [
        "filesystem.read"
      ],
      "resource_usage": {},
      "preflight_time": 0.0,
      "p4_time": 0.0,
      "execution_time": 0.15354371070861816,
      "total_time": 0.0,
      "final_status": "P4_ALLOW"
    },
    {
      "event_id": "226d6511-db31-4cad-9ec4-f7260c61035f",
      "session_id": "cap_workload",
      "sequence_no": 1,
      "correlation_id": "7b60bd90-4300-4552-922d-477c02d907c4",
      "preflight_valid": true,
      "preflight_reason": "preflight_passed",
      "preflight_rules_triggered": [],
      "risk_score": 0.1,
      "p4_verdict": "ALLOW",
      "p4_reason": "risk_within_threshold",
      "p4_risk_level": "low",
      "p4_rule_triggered": null,
      "execution_status": "SUCCESS",
      "execution_error": null,
      "capabilities_checked": [
        "filesystem.read"
      ],
      "resource_usage": {},
      "preflight_time": 0.0,
      "p4_time": 0.0,
      "execution_time": 0.004002571105957031,
      "total_time": 0.0,
      "final_status": "P4_ALLOW"
    },
    {
      "event_id": "b83765a4-aa45-4fd1-85cc-002840f871fd",
      "session_id": "cap_workload",
      "sequence_no": 1,
      "correlation_id": "78c5a36e-d205-4a51-ab7f-f201b54fe78a",
      "preflight_valid": true,
      "preflight_reason": "preflight_passed",
      "preflight_rules_triggered": [],
      "risk_score": 0.1,
      "p4_verdict": "ALLOW",
      "p4_reason": "risk_within_threshold",
      "p4_risk_level": "low",
      "p4_rule_triggered": null,
      "execution_status": "SUCCESS",
      "execution_error": null,
      "capabilities_checked": [
        "filesystem.read"
      ],
      "resource_usage": {},
      "preflight_time": 0.0,
      "p4_time": 0.0,
      "execution_time": 0.001001119613647461,
      "total_time": 0.0,
      "final_status": "P4_ALLOW"
    },
    {
      "event_id": "05e24fad-b7f1-4783-97d9-90f3548962c8",
      "session_id": "cap_workload",
      "sequence_no": 1,
      "correlation_id": "9bfe454b-1855-43fe-be63-1237e2fc49e4",
      "preflight_valid": true,
      "preflight_reason": "preflight_passed",
      "preflight_rules_triggered": [],
      "risk_score": 0.1,
      "p4_verdict": "ALLOW",
      "p4_reason": "risk_within_threshold",
      "p4_risk_level": "low",
      "p4_rule_triggered": null,
      "execution_status": "SUCCESS",
      "execution_error": null,
      "capabilities_checked": [
        "filesystem.read"
      ],
      "resource_usage": {},
      "preflight_time": 0.0,
      "p4_time": 0.0,
      "execution_time": 0.0010030269622802734,
      "total_time": 0.0,
      "final_status": "P4_ALLOW"
    },
    {
      "event_id": "0e27bcc4-8f28-4459-98f9-1431d585c841",
      "session_id": "cap_workload",
      "sequence_no": 1,
      "correlation_id": "e52555eb-dfab-48a1-8498-2439f76afc99",
      "preflight_valid": true,
      "preflight_reason": "preflight_passed",
      "preflight_rules_triggered": [],
      "risk_score": 0.1,
      "p4_verdict": "ALLOW",
      "p4_reason": "risk_within_threshold",
      "p4_risk_level": "low",
      "p4_rule_triggered": null,
      "execution_status": "SUCCESS",
      "execution_error": null,
      "capabilities_checked": [
        "filesystem.read"
      ],
      "resource_usage": {},
      "preflight_time": 0.0,
      "p4_time": 0.0,
      "execution_time": 0.02199554443359375,
      "total_time": 0.0,
      "final_status": "P4_ALLOW"
    },
    {
      "event_id": "7b8bf47c-6e55-42e2-957c-1084022533b1",
      "session_id": "cap_workload",
      "sequence_no": 1,
      "correlation_id": "99755ae9-0d17-41df-b313-1b39dc44452b",
      "preflight_valid": true,
      "preflight_reason": "preflight_passed",
      "preflight_rules_triggered": [],
      "risk_score": 0.1,
      "p4_verdict": "ALLOW",
      "p4_reason": "risk_within_threshold",
      "p4_risk_level": "low",
      "p4_rule_triggered": null,
      "execution_status": "SUCCESS",
      "execution_error": null,
      "capabilities_checked": [
        "filesystem.read"
      ],
      "resource_usage": {},
      "preflight_time": 0.0,
      "p4_time": 0.0,
      "execution_time": 0.15255260467529297,
      "total_time": 0.0,
      "final_status": "P4_ALLOW"
    },
    {
      "event_id": "17266cc6-30d9-424e-ac72-7d156e1fda02",
      "session_id": "cap_workload",
      "sequence_no": 1,
      "correlation_id": "9027c181-5ac5-4269-92ec-8ffd326b60b9",
      "preflight_valid": true,
      "preflight_reason": "preflight_passed",
      "preflight_rules_triggered": [],
      "risk_score": 0.1,
      "p4_verdict": "ALLOW",
      "p4_reason": "risk_within_threshold",
      "p4_risk_level": "low",
      "p4_rule_triggered": null,
      "execution_status": "SUCCESS",
      "execution_error": null,
      "capabilities_checked": [
        "filesystem.read"
      ],
      "resource_usage": {},
      "preflight_time": 0.0,
      "p4_time": 0.0,
      "execution_time": 0.010004043579101562,
      "total_time": 0.0,
      "final_status": "P4_ALLOW"
    },
    {
      "event_id": "ca7a7245-e8fa-4749-9986-69f26f9df577",
      "session_id": "cap_workload",
      "sequence_no": 1,
      "correlation_id": "9935c2d4-4677-408b-8db4-20d69da6825a",
      "preflight_valid": true,
      "preflight_reason": "preflight_passed",
      "preflight_rules_triggered": [],
      "risk_score": 0.1,
      "p4_verdict": "ALLOW",
      "p4_reason": "risk_within_threshold",
      "p4_risk_level": "low",
      "p4_rule_triggered": null,
      "execution_status": "SUCCESS",
      "execution_error": null,
      "capabilities_checked": [
        "filesystem.read"
      ],
      "resource_usage": {},
      "preflight_time": 0.0,
      "p4_time": 0.0,
      "execution_time": 0.0,
      "total_time": 0.0,
      "final_status": "P4_ALLOW"
    },
    {
      "event_id": "7d43b58c-58ae-4598-97a5-c19e40bea6a9",
      "session_id": "cap_workload",
      "sequence_no": 1,
      "correlation_id": "2556bcd2-6317-45b0-9924-2a42e6ecb802",
      "preflight_valid": true,
      "preflight_reason": "preflight_passed",
      "preflight_rules_triggered": [],
      "risk_score": 0.1,
      "p4_verdict": "ALLOW",
      "p4_reason": "risk_within_threshold",
      "p4_risk_level": "low",
      "p4_rule_triggered": null,
      "execution_status": "SUCCESS",
      "execution_error": null,
      "capabilities_checked": [
        "filesystem.read"
      ],
      "resource_usage": {},
      "preflight_time": 0.0,
      "p4_time": 0.0,
      "execution_time": 0.001004934310913086,
      "total_time": 0.0,
      "final_status": "P4_ALLOW"
    },
    {
      "event_id": "647bbb25-351d-4ca5-b3ce-e14efa877726",
      "session_id": "cap_workload",
      "sequence_no": 1,
      "correlation_id": "f22598aa-2466-40ef-b6cd-e5db7f610582",
      "preflight_valid": true,
      "preflight_reason": "preflight_passed",
      "preflight_rules_triggered": [],
      "risk_score": 0.1,
      "p4_verdict": "ALLOW",
      "p4_reason": "risk_within_threshold",
      "p4_risk_level": "low",
      "p4_rule_triggered": null,
      "execution_status": "SUCCESS",
      "execution_error": null,
      "capabilities_checked": [
        "filesystem.read"
      ],
      "resource_usage": {},
      "preflight_time": 0.0,
      "p4_time": 0.0,
      "execution_time": 0.011001348495483398,
      "total_time": 0.0,
      "final_status": "P4_ALLOW"
    },
    {
      "event_id": "8a66ffc1-b3f0-4b11-8ace-f65836a87da7",
      "session_id": "cap_workload",
      "sequence_no": 1,
      "correlation_id": "7f0665d6-7273-42e1-aa4e-db812568e82e",
      "preflight_valid": true,
      "preflight_reason": "preflight_passed",
      "preflight_rules_triggered": [],
      "risk_score": 0.1,
      "p4_verdict": "ALLOW",
      "p4_reason": "risk_within_threshold",
      "p4_risk_level": "low",
      "p4_rule_triggered": null,
      "execution_status": "SUCCESS",
      "execution_error": null,
      "capabilities_checked": [
        "filesystem.read"
      ],
      "resource_usage": {},
      "preflight_time": 0.0,
      "p4_time": 0.0,
      "execution_time": 0.13053607940673828,
      "total_time": 0.0,
      "final_status": "P4_ALLOW"
    },
    {
      "event_id": "423b00ba-8824-44a1-bca9-fd82ac5a05cf",
      "session_id": "cap_workload",
      "sequence_no": 1,
      "correlation_id": "31eda3a0-9260-4418-b160-411cf00c19c7",
      "preflight_valid": true,
      "preflight_reason": "preflight_passed",
      "preflight_rules_triggered": [],
      "risk_score": 0.1,
      "p4_verdict": "ALLOW",
      "p4_reason": "risk_within_threshold",
      "p4_risk_level": "low",
      "p4_rule_triggered": null,
      "execution_status": "SUCCESS",
      "execution_error": null,
      "capabilities_checked": [
        "filesystem.read"
      ],
      "resource_usage": {},
      "preflight_time": 0.0,
      "p4_time": 0.0,
      "execution_time": 0.006006002426147461,
      "total_time": 0.0,
      "final_status": "P4_ALLOW"
    },
    {
      "event_id": "dbc6380b-f160-407e-bc4d-53e2b7bb0e38",
      "session_id": "cap_workload",
      "sequence_no": 1,
      "correlation_id": "ce04a9b7-cb36-41db-b22d-7972a8ac9694",
      "preflight_valid": true,
      "preflight_reason": "preflight_passed",
      "preflight_rules_triggered": [],
      "risk_score": 0.1,
      "p4_verdict": "ALLOW",
      "p4_reason": "risk_within_threshold",
      "p4_risk_level": "low",
      "p4_rule_triggered": null,
      "execution_status": "SUCCESS",
      "execution_error": null,
      "capabilities_checked": [
        "filesystem.read"
      ],
      "resource_usage": {},
      "preflight_time": 0.0,
      "p4_time": 0.0,
      "execution_time": 0.0009975433349609375,
      "total_time": 0.0,
      "final_status": "P4_ALLOW"
    },
    {
      "event_id": "19619664-77f3-469d-9e77-9791c711901c",
      "session_id": "cap_workload",
      "sequence_no": 1,
      "correlation_id": "dd0d2a74-a6b3-4702-9716-b7e0d6635bfd",
      "preflight_valid": true,
      "preflight_reason": "preflight_passed",
      "preflight_rules_triggered": [],
      "risk_score": 0.1,
      "p4_verdict": "ALLOW",
      "p4_reason": "risk_within_threshold",
      "p4_risk_level": "low",
      "p4_rule_triggered": null,
      "execution_status": "SUCCESS",
      "execution_error": null,
      "capabilities_checked": [
        "filesystem.read"
      ],
      "resource_usage": {},
      "preflight_time": 0.0,
      "p4_time": 0.0,
      "execution_time": 0.002002239227294922,
      "total_time": 0.0,
      "final_status": "P4_ALLOW"
    },
    {
      "event_id": "e93ac0d5-ceb6-438b-a86e-6378d160d033",
      "session_id": "cap_workload",
      "sequence_no": 1,
      "correlation_id": "909564a7-9a07-4a2d-b8a6-0d93359e52c5",
      "preflight_valid": true,
      "preflight_reason": "preflight_passed",
      "preflight_rules_triggered": [],
      "risk_score": 0.1,
      "p4_verdict": "ALLOW",
      "p4_reason": "risk_within_threshold",
      "p4_risk_level": "low",
      "p4_rule_triggered": null,
      "execution_status": "SUCCESS",
      "execution_error": null,
      "capabilities_checked": [
        "filesystem.read"
      ],
      "resource_usage": {},
      "preflight_time": 0.0,
      "p4_time": 0.0,
      "execution_time": 0.016001224517822266,
      "total_time": 0.0,
      "final_status": "P4_ALLOW"
    },
    {
      "event_id": "981ba740-284c-4577-acfd-bb57c348b4fe",
      "session_id": "cap_workload",
      "sequence_no": 1,
      "correlation_id": "b5f718ac-d93a-4d65-9836-afdf93eee42f",
      "preflight_valid": true,
      "preflight_reason": "preflight_passed",
      "preflight_rules_triggered": [],
      "risk_score": 0.1,
      "p4_verdict": "ALLOW",
      "p4_reason": "risk_within_threshold",
      "p4_risk_level": "low",
      "p4_rule_triggered": null,
      "execution_status": "SUCCESS",
      "execution_error": null,
      "capabilities_checked": [
        "filesystem.read"
      ],
      "resource_usage": {},
      "preflight_time": 0.0,
      "p4_time": 0.0,
      "execution_time": 0.14754962921142578,
      "total_time": 0.0,
      "final_status": "P4_ALLOW"
    },
    {
      "event_id": "7394c1af-838a-4a83-abdf-472bc28dc361",
      "session_id": "cap_workload",
      "sequence_no": 1,
      "correlation_id": "bce69811-94e6-4834-b87b-5e49da3534d0",
      "preflight_valid": true,
      "preflight_reason": "preflight_passed",
      "preflight_rules_triggered": [],
      "risk_score": 0.1,
      "p4_verdict": "ALLOW",
      "p4_reason": "risk_within_threshold",
      "p4_risk_level": "low",
      "p4_rule_triggered": null,
      "execution_status": "SUCCESS",
      "execution_error": null,
      "capabilities_checked": [
        "filesystem.read"
      ],
      "resource_usage": {},
      "preflight_time": 0.0,
      "p4_time": 0.0,
      "execution_time": 0.003999471664428711,
      "total_time": 0.0,
      "final_status": "P4_ALLOW"
    },
    {
      "event_id": "701ced30-073f-4733-8bd1-4219f628f082",
      "session_id": "cap_workload",
      "sequence_no": 1,
      "correlation_id": "d2e35bfc-ab60-4d1c-8e9c-db0165e090ca",
      "preflight_valid": true,
      "preflight_reason": "preflight_passed",
      "preflight_rules_triggered": [],
      "risk_score": 0.1,
      "p4_verdict": "ALLOW",
      "p4_reason": "risk_within_threshold",
      "p4_risk_level": "low",
      "p4_rule_triggered": null,
      "execution_status": "SUCCESS",
      "execution_error": null,
      "capabilities_checked": [
        "filesystem.read"
      ],
      "resource_usage": {},
      "preflight_time": 0.0,
      "p4_time": 0.0,
      "execution_time": 0.001512765884399414,
      "total_time": 0.0,
      "final_status": "P4_ALLOW"
    },
    {
      "event_id": "3e73f811-0361-48b0-b49b-56a632092511",
      "session_id": "cap_workload",
      "sequence_no": 1,
      "correlation_id": "70d52501-af89-4798-af74-bce752aef542",
      "preflight_valid": true,
      "preflight_reason": "preflight_passed",
      "preflight_rules_triggered": [],
      "risk_score": 0.1,
      "p4_verdict": "ALLOW",
      "p4_reason": "risk_within_threshold",
      "p4_risk_level": "low",
      "p4_rule_triggered": null,
      "execution_status": "SUCCESS",
      "execution_error": null,
      "capabilities_checked": [
        "filesystem.read"
      ],
      "resource_usage": {},
      "preflight_time": 0.0,
      "p4_time": 0.0,
      "execution_time": 0.0,
      "total_time": 0.0,
      "final_status": "P4_ALLOW"
    },
    {
      "event_id": "823ea113-cceb-46f3-8e5f-283aa3ada41d",
      "session_id": "cap_workload",
      "sequence_no": 1,
      "correlation_id": "dccf4089-2647-4a80-b93d-2e1fc8d1dbb9",
      "preflight_valid": true,
      "preflight_reason": "preflight_passed",
      "preflight_rules_triggered": [],
      "risk_score": 0.1,
      "p4_verdict": "ALLOW",
      "p4_reason": "risk_within_threshold",
      "p4_risk_level": "low",
      "p4_rule_triggered": null,
      "execution_status": "SUCCESS",
      "execution_error": null,
      "capabilities_checked": [
        "filesystem.read"
      ],
      "resource_usage": {},
      "preflight_time": 0.0,
      "p4_time": 0.0,
      "execution_time": 0.03299832344055176,
      "total_time": 0.0,
      "final_status": "P4_ALLOW"
    },
    {
      "event_id": "d37d8e0b-a7a3-40b7-92e4-d0e9a8b6778d",
      "session_id": "cap_workload",
      "sequence_no": 1,
      "correlation_id": "16e56d71-7b0f-41a9-bd70-0903594a8443",
      "preflight_valid": true,
      "preflight_reason": "preflight_passed",
      "preflight_rules_triggered": [],
      "risk_score": 0.1,
      "p4_verdict": "ALLOW",
      "p4_reason": "risk_within_threshold",
      "p4_risk_level": "low",
      "p4_rule_triggered": null,
      "execution_status": "SUCCESS",
      "execution_error": null,
      "capabilities_checked": [
        "filesystem.read"
      ],
      "resource_usage": {},
      "preflight_time": 0.0,
      "p4_time": 0.0,
      "execution_time": 0.1315464973449707,
      "total_time": 0.0,
      "final_status": "P4_ALLOW"
    },
    {
      "event_id": "3b542b7d-59a2-4b65-9a38-1364e230c36f",
      "session_id": "cap_workload",
      "sequence_no": 1,
      "correlation_id": "0b49fcc6-e84c-403a-ae31-33f92b1c2846",
      "preflight_valid": true,
      "preflight_reason": "preflight_passed",
      "preflight_rules_triggered": [],
      "risk_score": 0.1,
      "p4_verdict": "ALLOW",
      "p4_reason": "risk_within_threshold",
      "p4_risk_level": "low",
      "p4_rule_triggered": null,
      "execution_status": "SUCCESS",
      "execution_error": null,
      "capabilities_checked": [
        "filesystem.read"
      ],
      "resource_usage": {},
      "preflight_time": 0.0,
      "p4_time": 0.0,
      "execution_time": 0.002995014190673828,
      "total_time": 0.0,
      "final_status": "P4_ALLOW"
    },
    {
      "event_id": "8a1e656e-5e70-46f1-abb6-29b1cfb3e42c",
      "session_id": "cap_workload",
      "sequence_no": 1,
      "correlation_id": "ae9aa491-e9a5-4d6a-a508-1023a4f84cc8",
      "preflight_valid": true,
      "preflight_reason": "preflight_passed",
      "preflight_rules_triggered": [],
      "risk_score": 0.1,
      "p4_verdict": "ALLOW",
      "p4_reason": "risk_within_threshold",
      "p4_risk_level": "low",
      "p4_rule_triggered": null,
      "execution_status": "SUCCESS",
      "execution_error": null,
      "capabilities_checked": [
        "filesystem.read"
      ],
      "resource_usage": {},
      "preflight_time": 0.0,
      "p4_time": 0.0,
      "execution_time": 0.0060007572174072266,
      "total_time": 0.0,
      "final_status": "P4_ALLOW"
    },
    {
      "event_id": "f5087b77-82cb-4219-8eb6-f7251f7cafd2",
      "session_id": "cap_workload",
      "sequence_no": 1,
      "correlation_id": "2b35cbd4-ab0b-4495-8261-cebf8f01198f",
      "preflight_valid": true,
      "preflight_reason": "preflight_passed",
      "preflight_rules_triggered": [],
      "risk_score": 0.1,
      "p4_verdict": "ALLOW",
      "p4_reason": "risk_within_threshold",
      "p4_risk_level": "low",
      "p4_rule_triggered": null,
      "execution_status": "SUCCESS",
      "execution_error": null,
      "capabilities_checked": [
        "filesystem.read"
      ],
      "resource_usage": {},
      "preflight_time": 0.0,
      "p4_time": 0.0,
      "execution_time": 0.0029954910278320312,
      "total_time": 0.0,
      "final_status": "P4_ALLOW"
    },
    {
      "event_id": "c4082cad-4db2-4fa5-86b2-83d3620db750",
      "session_id": "cap_workload",
      "sequence_no": 1,
      "correlation_id": "cc08d68c-3ed4-47e0-a440-f313da764106",
      "preflight_valid": true,
      "preflight_reason": "preflight_passed",
      "preflight_rules_triggered": [],
      "risk_score": 0.1,
      "p4_verdict": "ALLOW",
      "p4_reason": "risk_within_threshold",
      "p4_risk_level": "low",
      "p4_rule_triggered": null,
      "execution_status": "SUCCESS",
      "execution_error": null,
      "capabilities_checked": [
        "filesystem.read"
      ],
      "resource_usage": {},
      "preflight_time": 0.0,
      "p4_time": 0.0,
      "execution_time": 0.027002573013305664,
      "total_time": 0.0,
      "final_status": "P4_ALLOW"
    },
    {
      "event_id": "33a59cbe-3254-45dd-8140-400102159f85",
      "session_id": "cap_workload",
      "sequence_no": 1,
      "correlation_id": "6c5c68e1-d7fd-4468-b762-3e6e287562a6",
      "preflight_valid": true,
      "preflight_reason": "preflight_passed",
      "preflight_rules_triggered": [],
      "risk_score": 0.1,
      "p4_verdict": "ALLOW",
      "p4_reason": "risk_within_threshold",
      "p4_risk_level": "low",
      "p4_rule_triggered": null,
      "execution_status": "SUCCESS",
      "execution_error": null,
      "capabilities_checked": [
        "filesystem.read"
      ],
      "resource_usage": {},
      "preflight_time": 0.0,
      "p4_time": 0.0,
      "execution_time": 0.11754822731018066,
      "total_time": 0.0,
      "final_status": "P4_ALLOW"
    },
    {
      "event_id": "f6abc77d-b5d2-435f-8998-02a74835a75c",
      "session_id": "cap_workload",
      "sequence_no": 1,
      "correlation_id": "10c54f52-0c55-4066-bd45-0b45966a38bd",
      "preflight_valid": true,
      "preflight_reason": "preflight_passed",
      "preflight_rules_triggered": [],
      "risk_score": 0.1,
      "p4_verdict": "ALLOW",
      "p4_reason": "risk_within_threshold",
      "p4_risk_level": "low",
      "p4_rule_triggered": null,
      "execution_status": "SUCCESS",
      "execution_error": null,
      "capabilities_checked": [
        "filesystem.read"
      ],
      "resource_usage": {},
      "preflight_time": 0.0,
      "p4_time": 0.0,
      "execution_time": 0.016524314880371094,
      "total_time": 0.0,
      "final_status": "P4_ALLOW"
    },
    {
      "event_id": "498aaa8f-4da5-460b-ab17-96e599146bcf",
      "session_id": "cap_workload",
      "sequence_no": 1,
      "correlation_id": "57bbf279-8c9c-43ce-9a9d-eb8a87a3506f",
      "preflight_valid": true,
      "preflight_reason": "preflight_passed",
      "preflight_rules_triggered": [],
      "risk_score": 0.1,
      "p4_verdict": "ALLOW",
      "p4_reason": "risk_within_threshold",
      "p4_risk_level": "low",
      "p4_rule_triggered": null,
      "execution_status": "SUCCESS",
      "execution_error": null,
      "capabilities_checked": [
        "filesystem.read"
      ],
      "resource_usage": {},
      "preflight_time": 0.0,
      "p4_time": 0.0,
      "execution_time": 0.0010039806365966797,
      "total_time": 0.0,
      "final_status": "P4_ALLOW"
    },
    {
      "event_id": "5da2fd0c-a317-4b87-a6a7-38ed59edab8b",
      "session_id": "cap_workload",
      "sequence_no": 1,
      "correlation_id": "ac62f1a0-c812-4be3-8d21-7b63baa94962",
      "preflight_valid": true,
      "preflight_reason": "preflight_passed",
      "preflight_rules_triggered": [],
      "risk_score": 0.1,
      "p4_verdict": "ALLOW",
      "p4_reason": "risk_within_threshold",
      "p4_risk_level": "low",
      "p4_rule_triggered": null,
      "execution_status": "SUCCESS",
      "execution_error": null,
      "capabilities_checked": [
        "filesystem.read"
      ],
      "resource_usage": {},
      "preflight_time": 0.0,
      "p4_time": 0.0,
      "execution_time": 0.0009963512420654297,
      "total_time": 0.0,
      "final_status": "P4_ALLOW"
    },
    {
      "event_id": "a59d7794-4ea2-475a-9576-a91d1209e085",
      "session_id": "cap_workload",
      "sequence_no": 1,
      "correlation_id": "d967170a-900a-464c-a4b9-a8280d66ae3c",
      "preflight_valid": true,
      "preflight_reason": "preflight_passed",
      "preflight_rules_triggered": [],
      "risk_score": 0.1,
      "p4_verdict": "ALLOW",
      "p4_reason": "risk_within_threshold",
      "p4_risk_level": "low",
      "p4_rule_triggered": null,
      "execution_status": "SUCCESS",
      "execution_error": null,
      "capabilities_checked": [
        "filesystem.read"
      ],
      "resource_usage": {},
      "preflight_time": 0.0,
      "p4_time": 0.0,
      "execution_time": 0.013997793197631836,
      "total_time": 0.0,
      "final_status": "P4_ALLOW"
    },
    {
      "event_id": "9fd638ed-520b-417b-aa81-cca1413d5022",
      "session_id": "cap_workload",
      "sequence_no": 1,
      "correlation_id": "4961af61-83c8-419c-a701-98ae79e0a5f9",
      "preflight_valid": true,
      "preflight_reason": "preflight_passed",
      "preflight_rules_triggered": [],
      "risk_score": 0.1,
      "p4_verdict": "ALLOW",
      "p4_reason": "risk_within_threshold",
      "p4_risk_level": "low",
      "p4_rule_triggered": null,
      "execution_status": "SUCCESS",
      "execution_error": null,
      "capabilities_checked": [
        "filesystem.read"
      ],
      "resource_usage": {},
      "preflight_time": 0.0,
      "p4_time": 0.0,
      "execution_time": 0.11358332633972168,
      "total_time": 0.0,
      "final_status": "P4_ALLOW"
    },
    {
      "event_id": "c1201d9e-1446-4aab-86d6-1979280805a7",
      "session_id": "cap_workload",
      "sequence_no": 1,
      "correlation_id": "c0e771f0-1b17-4360-b5c3-e7938d8bd1ff",
      "preflight_valid": true,
      "preflight_reason": "preflight_passed",
      "preflight_rules_triggered": [],
      "risk_score": 0.1,
      "p4_verdict": "ALLOW",
      "p4_reason": "risk_within_threshold",
      "p4_risk_level": "low",
      "p4_rule_triggered": null,
      "execution_status": "SUCCESS",
      "execution_error": null,
      "capabilities_checked": [
        "filesystem.read"
      ],
      "resource_usage": {},
      "preflight_time": 0.0,
      "p4_time": 0.0,
      "execution_time": 0.005995988845825195,
      "total_time": 0.0,
      "final_status": "P4_ALLOW"
    },
    {
      "event_id": "34af9fb1-11a0-4c71-b0de-a991c691107a",
      "session_id": "cap_workload",
      "sequence_no": 1,
      "correlation_id": "af7a92e5-8674-4d29-96dd-416f8ba7730f",
      "preflight_valid": true,
      "preflight_reason": "preflight_passed",
      "preflight_rules_triggered": [],
      "risk_score": 0.1,
      "p4_verdict": "ALLOW",
      "p4_reason": "risk_within_threshold",
      "p4_risk_level": "low",
      "p4_rule_triggered": null,
      "execution_status": "SUCCESS",
      "execution_error": null,
      "capabilities_checked": [
        "filesystem.read"
      ],
      "resource_usage": {},
      "preflight_time": 0.0,
      "p4_time": 0.0,
      "execution_time": 0.0,
      "total_time": 0.0,
      "final_status": "P4_ALLOW"
    },
    {
      "event_id": "d05c858a-d041-400a-bb5c-ee631653278e",
      "session_id": "cap_workload",
      "sequence_no": 1,
      "correlation_id": "d17d83f3-05eb-45c3-ade7-3369784fdbf4",
      "preflight_valid": true,
      "preflight_reason": "preflight_passed",
      "preflight_rules_triggered": [],
      "risk_score": 0.1,
      "p4_verdict": "ALLOW",
      "p4_reason": "risk_within_threshold",
      "p4_risk_level": "low",
      "p4_rule_triggered": null,
      "execution_status": "SUCCESS",
      "execution_error": null,
      "capabilities_checked": [
        "filesystem.read"
      ],
      "resource_usage": {},
      "preflight_time": 0.0,
      "p4_time": 0.0,
      "execution_time": 0.004003047943115234,
      "total_time": 0.0,
      "final_status": "P4_ALLOW"
    },
    {
      "event_id": "2d49823c-b3e8-4747-8a21-0c2c817b32fd",
      "session_id": "cap_workload",
      "sequence_no": 1,
      "correlation_id": "2b95f106-831f-4b0a-8a30-323cc297775f",
      "preflight_valid": true,
      "preflight_reason": "preflight_passed",
      "preflight_rules_triggered": [],
      "risk_score": 0.1,
      "p4_verdict": "ALLOW",
      "p4_reason": "risk_within_threshold",
      "p4_risk_level": "low",
      "p4_rule_triggered": null,
      "execution_status": "SUCCESS",
      "execution_error": null,
      "capabilities_checked": [
        "filesystem.read"
      ],
      "resource_usage": {},
      "preflight_time": 0.0,
      "p4_time": 0.0,
      "execution_time": 0.02600240707397461,
      "total_time": 0.0,
      "final_status": "P4_ALLOW"
    },
    {
      "event_id": "88030e14-b566-4296-9b21-ee5cbc771dd6",
      "session_id": "cap_workload",
      "sequence_no": 1,
      "correlation_id": "3cd04274-7dd6-4047-ae95-381c1f77c867",
      "preflight_valid": true,
      "preflight_reason": "preflight_passed",
      "preflight_rules_triggered": [],
      "risk_score": 0.1,
      "p4_verdict": "ALLOW",
      "p4_reason": "risk_within_threshold",
      "p4_risk_level": "low",
      "p4_rule_triggered": null,
      "execution_status": "SUCCESS",
      "execution_error": null,
      "capabilities_checked": [
        "filesystem.read"
      ],
      "resource_usage": {},
      "preflight_time": 0.0,
      "p4_time": 0.0,
      "execution_time": 0.11605358123779297,
      "total_time": 0.0,
      "final_status": "P4_ALLOW"
    },
    {
      "event_id": "03c1965f-890c-466d-beb9-73c9b258fcb7",
      "session_id": "cap_workload",
      "sequence_no": 1,
      "correlation_id": "37dc6bde-a197-4984-b109-93a0fd2b4fed",
      "preflight_valid": true,
      "preflight_reason": "preflight_passed",
      "preflight_rules_triggered": [],
      "risk_score": 0.1,
      "p4_verdict": "ALLOW",
      "p4_reason": "risk_within_threshold",
      "p4_risk_level": "low",
      "p4_rule_triggered": null,
      "execution_status": "SUCCESS",
      "execution_error": null,
      "capabilities_checked": [
        "filesystem.read"
      ],
      "resource_usage": {},
      "preflight_time": 0.0,
      "p4_time": 0.0,
      "execution_time": 0.004003286361694336,
      "total_time": 0.0,
      "final_status": "P4_ALLOW"
    },
    {
      "event_id": "2c921f2a-d829-4f63-8a32-eabdffc0eab1",
      "session_id": "cap_workload",
      "sequence_no": 1,
      "correlation_id": "7935da96-fc86-45e0-8c89-0bd21d1154bd",
      "preflight_valid": true,
      "preflight_reason": "preflight_passed",
      "preflight_rules_triggered": [],
      "risk_score": 0.1,
      "p4_verdict": "ALLOW",
      "p4_reason": "risk_within_threshold",
      "p4_risk_level": "low",
      "p4_rule_triggered": null,
      "execution_status": "SUCCESS",
      "execution_error": null,
      "capabilities_checked": [
        "filesystem.read"
      ],
      "resource_usage": {},
      "preflight_time": 0.0,
      "p4_time": 0.0,
      "execution_time": 0.0,
      "total_time": 0.0,
      "final_status": "P4_ALLOW"
    },
    {
      "event_id": "40a16213-9c0a-42f1-89d9-ed7331214659",
      "session_id": "cap_workload",
      "sequence_no": 1,
      "correlation_id": "1fd1df27-e4fe-4708-97f7-844f925f0264",
      "preflight_valid": true,
      "preflight_reason": "preflight_passed",
      "preflight_rules_triggered": [],
      "risk_score": 0.1,
      "p4_verdict": "ALLOW",
      "p4_reason": "risk_within_threshold",
      "p4_risk_level": "low",
      "p4_rule_triggered": null,
      "execution_status": "SUCCESS",
      "execution_error": null,
      "capabilities_checked": [
        "filesystem.read"
      ],
      "resource_usage": {},
      "preflight_time": 0.0,
      "p4_time": 0.0,
      "execution_time": 0.0009875297546386719,
      "total_time": 0.0,
      "final_status": "P4_ALLOW"
    },
    {
      "event_id": "ace7c7a1-c447-4105-b0f8-2bc81802ee54",
      "session_id": "cap_workload",
      "sequence_no": 1,
      "correlation_id": "8c68ea29-4357-4ec8-8774-0fe97a028357",
      "preflight_valid": true,
      "preflight_reason": "preflight_passed",
      "preflight_rules_triggered": [],
      "risk_score": 0.1,
      "p4_verdict": "ALLOW",
      "p4_reason": "risk_within_threshold",
      "p4_risk_level": "low",
      "p4_rule_triggered": null,
      "execution_status": "SUCCESS",
      "execution_error": null,
      "capabilities_checked": [
        "filesystem.read"
      ],
      "resource_usage": {},
      "preflight_time": 0.0,
      "p4_time": 0.0,
      "execution_time": 0.012995481491088867,
      "total_time": 0.0,
      "final_status": "P4_ALLOW"
    },
    {
      "event_id": "7269982c-310b-4257-a8e6-967bfc58e745",
      "session_id": "cap_workload",
      "sequence_no": 1,
      "correlation_id": "18dd0aa2-3113-46cc-9f52-f4052e796bfd",
      "preflight_valid": true,
      "preflight_reason": "preflight_passed",
      "preflight_rules_triggered": [],
      "risk_score": 0.1,
      "p4_verdict": "ALLOW",
      "p4_reason": "risk_within_threshold",
      "p4_risk_level": "low",
      "p4_rule_triggered": null,
      "execution_status": "SUCCESS",
      "execution_error": null,
      "capabilities_checked": [
        "filesystem.read"
      ],
      "resource_usage": {},
      "preflight_time": 0.0,
      "p4_time": 0.0,
      "execution_time": 0.18055462837219238,
      "total_time": 0.0,
      "final_status": "P4_ALLOW"
    },
    {
      "event_id": "641ced10-32e4-4e06-91e2-54e65f27f9ab",
      "session_id": "cap_workload",
      "sequence_no": 1,
      "correlation_id": "4111b1d1-eff9-493f-9d89-d2c8eda796de",
      "preflight_valid": true,
      "preflight_reason": "preflight_passed",
      "preflight_rules_triggered": [],
      "risk_score": 0.1,
      "p4_verdict": "ALLOW",
      "p4_reason": "risk_within_threshold",
      "p4_risk_level": "low",
      "p4_rule_triggered": null,
      "execution_status": "SUCCESS",
      "execution_error": null,
      "capabilities_checked": [
        "filesystem.read"
      ],
      "resource_usage": {},
      "preflight_time": 0.0,
      "p4_time": 0.0,
      "execution_time": 0.018012046813964844,
      "total_time": 0.0,
      "final_status": "P4_ALLOW"
    },
    {
      "event_id": "1b2bf88e-bb43-4dbe-8aa5-09645d9328ff",
      "session_id": "cap_workload",
      "sequence_no": 1,
      "correlation_id": "d5350388-7dfb-44e4-8201-750bd8ed3148",
      "preflight_valid": true,
      "preflight_reason": "preflight_passed",
      "preflight_rules_triggered": [],
      "risk_score": 0.1,
      "p4_verdict": "ALLOW",
      "p4_reason": "risk_within_threshold",
      "p4_risk_level": "low",
      "p4_rule_triggered": null,
      "execution_status": "SUCCESS",
      "execution_error": null,
      "capabilities_checked": [
        "filesystem.read"
      ],
      "resource_usage": {},
      "preflight_time": 0.0,
      "p4_time": 0.0,
      "execution_time": 0.0020051002502441406,
      "total_time": 0.0,
      "final_status": "P4_ALLOW"
    },
    {
      "event_id": "6fc106b2-40c0-4893-b0dc-51964c8adf8b",
      "session_id": "cap_workload",
      "sequence_no": 1,
      "correlation_id": "21bdbb42-9d1d-4d9e-9037-efb3e6ebc0b2",
      "preflight_valid": true,
      "preflight_reason": "preflight_passed",
      "preflight_rules_triggered": [],
      "risk_score": 0.1,
      "p4_verdict": "ALLOW",
      "p4_reason": "risk_within_threshold",
      "p4_risk_level": "low",
      "p4_rule_triggered": null,
      "execution_status": "SUCCESS",
      "execution_error": null,
      "capabilities_checked": [
        "filesystem.read"
      ],
      "resource_usage": {},
      "preflight_time": 0.0,
      "p4_time": 0.0,
      "execution_time": 0.0009911060333251953,
      "total_time": 0.0,
      "final_status": "P4_ALLOW"
    },
    {
      "event_id": "90689a7b-b99e-422b-8377-92709897c357",
      "session_id": "cap_workload",
      "sequence_no": 1,
      "correlation_id": "50e0237e-3758-4d71-a5b5-3912c2e260a5",
      "preflight_valid": true,
      "preflight_reason": "preflight_passed",
      "preflight_rules_triggered": [],
      "risk_score": 0.1,
      "p4_verdict": "ALLOW",
      "p4_reason": "risk_within_threshold",
      "p4_risk_level": "low",
      "p4_rule_triggered": null,
      "execution_status": "SUCCESS",
      "execution_error": null,
      "capabilities_checked": [
        "filesystem.read"
      ],
      "resource_usage": {},
      "preflight_time": 0.0,
      "p4_time": 0.0,
      "execution_time": 0.03152298927307129,
      "total_time": 0.0,
      "final_status": "P4_ALLOW"
    },
    {
      "event_id": "b82882d6-9b3c-4901-977a-2378284af89c",
      "session_id": "cap_workload",
      "sequence_no": 1,
      "correlation_id": "b1edfc5f-d2fd-4f33-bfe7-cda6784ac9e1",
      "preflight_valid": true,
      "preflight_reason": "preflight_passed",
      "preflight_rules_triggered": [],
      "risk_score": 0.1,
      "p4_verdict": "ALLOW",
      "p4_reason": "risk_within_threshold",
      "p4_risk_level": "low",
      "p4_rule_triggered": null,
      "execution_status": "SUCCESS",
      "execution_error": null,
      "capabilities_checked": [
        "filesystem.read"
      ],
      "resource_usage": {},
      "preflight_time": 0.0,
      "p4_time": 0.0,
      "execution_time": 0.12753939628601074,
      "total_time": 0.0,
      "final_status": "P4_ALLOW"
    },
    {
      "event_id": "a1b3176c-515b-467e-8734-7a3b51f62328",
      "session_id": "cap_workload",
      "sequence_no": 1,
      "correlation_id": "a65e1ddd-fcfc-44a1-a87f-e05761403ca7",
      "preflight_valid": true,
      "preflight_reason": "preflight_passed",
      "preflight_rules_triggered": [],
      "risk_score": 0.1,
      "p4_verdict": "ALLOW",
      "p4_reason": "risk_within_threshold",
      "p4_risk_level": "low",
      "p4_rule_triggered": null,
      "execution_status": "SUCCESS",
      "execution_error": null,
      "capabilities_checked": [
        "filesystem.read"
      ],
      "resource_usage": {},
      "preflight_time": 0.0,
      "p4_time": 0.0,
      "execution_time": 0.003999471664428711,
      "total_time": 0.0,
      "final_status": "P4_ALLOW"
    },
    {
      "event_id": "65d8dce5-eba6-46a0-bd30-480088124422",
      "session_id": "cap_workload",
      "sequence_no": 1,
      "correlation_id": "dc75c44c-7ab2-4d18-b869-2f4c5614a061",
      "preflight_valid": true,
      "preflight_reason": "preflight_passed",
      "preflight_rules_triggered": [],
      "risk_score": 0.1,
      "p4_verdict": "ALLOW",
      "p4_reason": "risk_within_threshold",
      "p4_risk_level": "low",
      "p4_rule_triggered": null,
      "execution_status": "SUCCESS",
      "execution_error": null,
      "capabilities_checked": [
        "filesystem.read"
      ],
      "resource_usage": {},
      "preflight_time": 0.0,
      "p4_time": 0.0,
      "execution_time": 0.0,
      "total_time": 0.0,
      "final_status": "P4_ALLOW"
    },
    {
      "event_id": "54cb537c-902d-46f5-99aa-115b7ddea4b8",
      "session_id": "cap_workload",
      "sequence_no": 1,
      "correlation_id": "cfebcbf1-c340-4c1f-8477-9d27b0c2f7d9",
      "preflight_valid": true,
      "preflight_reason": "preflight_passed",
      "preflight_rules_triggered": [],
      "risk_score": 0.1,
      "p4_verdict": "ALLOW",
      "p4_reason": "risk_within_threshold",
      "p4_risk_level": "low",
      "p4_rule_triggered": null,
      "execution_status": "SUCCESS",
      "execution_error": null,
      "capabilities_checked": [
        "filesystem.read"
      ],
      "resource_usage": {},
      "preflight_time": 0.0,
      "p4_time": 0.0,
      "execution_time": 0.001003265380859375,
      "total_time": 0.0,
      "final_status": "P4_ALLOW"
    },
    {
      "event_id": "bebc64b4-8f9f-4bde-b87d-ae8b66f98b27",
      "session_id": "cap_workload",
      "sequence_no": 1,
      "correlation_id": "39b2a245-e57f-4d1d-ac0a-45de53e5037b",
      "preflight_valid": true,
      "preflight_reason": "preflight_passed",
      "preflight_rules_triggered": [],
      "risk_score": 0.1,
      "p4_verdict": "ALLOW",
      "p4_reason": "risk_within_threshold",
      "p4_risk_level": "low",
      "p4_rule_triggered": null,
      "execution_status": "SUCCESS",
      "execution_error": null,
      "capabilities_checked": [
        "filesystem.read"
      ],
      "resource_usage": {},
      "preflight_time": 0.0,
      "p4_time": 0.0,
      "execution_time": 0.019003868103027344,
      "total_time": 0.0,
      "final_status": "P4_ALLOW"
    },
    {
      "event_id": "28bc739a-32fb-475f-9776-45b1213b797f",
      "session_id": "cap_workload",
      "sequence_no": 1,
      "correlation_id": "9ca74703-f656-432e-ba2d-ad031e58cf36",
      "preflight_valid": true,
      "preflight_reason": "preflight_passed",
      "preflight_rules_triggered": [],
      "risk_score": 0.1,
      "p4_verdict": "ALLOW",
      "p4_reason": "risk_within_threshold",
      "p4_risk_level": "low",
      "p4_rule_triggered": null,
      "execution_status": "SUCCESS",
      "execution_error": null,
      "capabilities_checked": [
        "filesystem.read"
      ],
      "resource_usage": {},
      "preflight_time": 0.0,
      "p4_time": 0.0,
      "execution_time": 0.16110682487487793,
      "total_time": 0.0,
      "final_status": "P4_ALLOW"
    },
    {
      "event_id": "0d5bb8ff-c7cf-4ec0-8b02-76d32c35e491",
      "session_id": "cap_workload",
      "sequence_no": 1,
      "correlation_id": "61e6b276-a37f-4be8-8ebc-1e74b0f8333e",
      "preflight_valid": true,
      "preflight_reason": "preflight_passed",
      "preflight_rules_triggered": [],
      "risk_score": 0.1,
      "p4_verdict": "ALLOW",
      "p4_reason": "risk_within_threshold",
      "p4_risk_level": "low",
      "p4_rule_triggered": null,
      "execution_status": "SUCCESS",
      "execution_error": null,
      "capabilities_checked": [
        "filesystem.read"
      ],
      "resource_usage": {},
      "preflight_time": 0.0,
      "p4_time": 0.0,
      "execution_time": 0.008018970489501953,
      "total_time": 0.0,
      "final_status": "P4_ALLOW"
    },
    {
      "event_id": "0e034930-0a8b-4f7f-b234-de3b71b03dc1",
      "session_id": "cap_workload",
      "sequence_no": 1,
      "correlation_id": "9e50ff94-4eec-4c90-acaa-3b255e56a7e7",
      "preflight_valid": true,
      "preflight_reason": "preflight_passed",
      "preflight_rules_triggered": [],
      "risk_score": 0.1,
      "p4_verdict": "ALLOW",
      "p4_reason": "risk_within_threshold",
      "p4_risk_level": "low",
      "p4_rule_triggered": null,
      "execution_status": "SUCCESS",
      "execution_error": null,
      "capabilities_checked": [
        "filesystem.read"
      ],
      "resource_usage": {},
      "preflight_time": 0.0,
      "p4_time": 0.0,
      "execution_time": 0.006998777389526367,
      "total_time": 0.0,
      "final_status": "P4_ALLOW"
    },
    {
      "event_id": "12739882-a887-442c-b175-80f3af265310",
      "session_id": "cap_workload",
      "sequence_no": 1,
      "correlation_id": "81c453a1-e66b-4ec9-b979-87c607d78238",
      "preflight_valid": true,
      "preflight_reason": "preflight_passed",
      "preflight_rules_triggered": [],
      "risk_score": 0.1,
      "p4_verdict": "ALLOW",
      "p4_reason": "risk_within_threshold",
      "p4_risk_level": "low",
      "p4_rule_triggered": null,
      "execution_status": "SUCCESS",
      "execution_error": null,
      "capabilities_checked": [
        "filesystem.read"
      ],
      "resource_usage": {},
      "preflight_time": 0.0,
      "p4_time": 0.0,
      "execution_time": 0.0009932518005371094,
      "total_time": 0.0,
      "final_status": "P4_ALLOW"
    },
    {
      "event_id": "49778fff-8421-409f-8887-f377c1c823fa",
      "session_id": "cap_workload",
      "sequence_no": 1,
      "correlation_id": "fe783a7c-bff6-4d45-9c68-4bf286f08934",
      "preflight_valid": true,
      "preflight_reason": "preflight_passed",
      "preflight_rules_triggered": [],
      "risk_score": 0.1,
      "p4_verdict": "ALLOW",
      "p4_reason": "risk_within_threshold",
      "p4_risk_level": "low",
      "p4_rule_triggered": null,
      "execution_status": "SUCCESS",
      "execution_error": null,
      "capabilities_checked": [
        "filesystem.read"
      ],
      "resource_usage": {},
      "preflight_time": 0.0,
      "p4_time": 0.0,
      "execution_time": 0.008993864059448242,
      "total_time": 0.0,
      "final_status": "P4_ALLOW"
    },
    {
      "event_id": "f418fb0c-3044-43d4-9a75-faf959fb7a4f",
      "session_id": "cap_workload",
      "sequence_no": 1,
      "correlation_id": "064ec59b-3d8f-4daf-9a18-8521586780fa",
      "preflight_valid": true,
      "preflight_reason": "preflight_passed",
      "preflight_rules_triggered": [],
      "risk_score": 0.1,
      "p4_verdict": "ALLOW",
      "p4_reason": "risk_within_threshold",
      "p4_risk_level": "low",
      "p4_rule_triggered": null,
      "execution_status": "SUCCESS",
      "execution_error": null,
      "capabilities_checked": [
        "filesystem.read"
      ],
      "resource_usage": {},
      "preflight_time": 0.0,
      "p4_time": 0.0,
      "execution_time": 0.14453744888305664,
      "total_time": 0.0,
      "final_status": "P4_ALLOW"
    },
    {
      "event_id": "02f6f896-ff90-4eb7-be85-24c1026fd4c5",
      "session_id": "cap_workload",
      "sequence_no": 1,
      "correlation_id": "0e2ab048-f4c1-4ea5-81d5-f8aa9e0df29f",
      "preflight_valid": true,
      "preflight_reason": "preflight_passed",
      "preflight_rules_triggered": [],
      "risk_score": 0.1,
      "p4_verdict": "ALLOW",
      "p4_reason": "risk_within_threshold",
      "p4_risk_level": "low",
      "p4_rule_triggered": null,
      "execution_status": "SUCCESS",
      "execution_error": null,
      "capabilities_checked": [
        "filesystem.read"
      ],
      "resource_usage": {},
      "preflight_time": 0.0,
      "p4_time": 0.0,
      "execution_time": 0.011998176574707031,
      "total_time": 0.0,
      "final_status": "P4_ALLOW"
    },
    {
      "event_id": "247fa471-c840-42a5-a807-408445ebb397",
      "session_id": "cap_workload",
      "sequence_no": 1,
      "correlation_id": "ba6b1d53-c554-4f60-b52d-17a8dac93e5b",
      "preflight_valid": true,
      "preflight_reason": "preflight_passed",
      "preflight_rules_triggered": [],
      "risk_score": 0.1,
      "p4_verdict": "ALLOW",
      "p4_reason": "risk_within_threshold",
      "p4_risk_level": "low",
      "p4_rule_triggered": null,
      "execution_status": "SUCCESS",
      "execution_error": null,
      "capabilities_checked": [
        "filesystem.read"
      ],
      "resource_usage": {},
      "preflight_time": 0.0,
      "p4_time": 0.0,
      "execution_time": 0.0,
      "total_time": 0.0,
      "final_status": "P4_ALLOW"
    },
    {
      "event_id": "babc8dad-284d-4e36-86c3-b76d79ea4b1a",
      "session_id": "cap_workload",
      "sequence_no": 1,
      "correlation_id": "8e9911fa-6e4f-4a80-9731-2d2356848f28",
      "preflight_valid": true,
      "preflight_reason": "preflight_passed",
      "preflight_rules_triggered": [],
      "risk_score": 0.1,
      "p4_verdict": "ALLOW",
      "p4_reason": "risk_within_threshold",
      "p4_risk_level": "low",
      "p4_rule_triggered": null,
      "execution_status": "SUCCESS",
      "execution_error": null,
      "capabilities_checked": [
        "filesystem.read"
      ],
      "resource_usage": {},
      "preflight_time": 0.0,
      "p4_time": 0.0,
      "execution_time": 0.0009984970092773438,
      "total_time": 0.0,
      "final_status": "P4_ALLOW"
    },
    {
      "event_id": "6d6dc09f-4e3a-4667-928a-73870b46cfb1",
      "session_id": "cap_workload",
      "sequence_no": 1,
      "correlation_id": "cc3f0402-5160-4529-86da-6086f71605c1",
      "preflight_valid": true,
      "preflight_reason": "preflight_passed",
      "preflight_rules_triggered": [],
      "risk_score": 0.1,
      "p4_verdict": "ALLOW",
      "p4_reason": "risk_within_threshold",
      "p4_risk_level": "low",
      "p4_rule_triggered": null,
      "execution_status": "SUCCESS",
      "execution_error": null,
      "capabilities_checked": [
        "filesystem.read"
      ],
      "resource_usage": {},
      "preflight_time": 0.0,
      "p4_time": 0.0,
      "execution_time": 0.01900458335876465,
      "total_time": 0.0,
      "final_status": "P4_ALLOW"
    },
    {
      "event_id": "78bec553-ef33-419d-8f23-3d995265fb0b",
      "session_id": "cap_workload",
      "sequence_no": 1,
      "correlation_id": "521db765-9238-44bd-8313-ed578722835a",
      "preflight_valid": true,
      "preflight_reason": "preflight_passed",
      "preflight_rules_triggered": [],
      "risk_score": 0.1,
      "p4_verdict": "ALLOW",
      "p4_reason": "risk_within_threshold",
      "p4_risk_level": "low",
      "p4_rule_triggered": null,
      "execution_status": "SUCCESS",
      "execution_error": null,
      "capabilities_checked": [
        "filesystem.read"
      ],
      "resource_usage": {},
      "preflight_time": 0.0,
      "p4_time": 0.0,
      "execution_time": 0.12355637550354004,
      "total_time": 0.0,
      "final_status": "P4_ALLOW"
    }
  ],
  "new_governance_scores": [
    0.0315,
    0.0313,
    0.0312
  ],
  "new_confidence_scores": [
    0.946,
    0.9231,
    0.911,
    0.9238
  ],
  "new_stability_scores": [
    0.75,
    0.75,
    0.75,
    0.75,
    0.75,
    0.75
  ],
  "runtime_state_snapshot": {
    "status": "running",
    "uptime_seconds": 0.0,
    "queue_depth": 601,
    "total_events_processed": 399,
    "active_sessions": 0,
    "health_status": "healthy",
    "consecutive_failures": 0,
    "drift_detected": false,
    "average_cycle_ms": 39.5,
    "last_error": null
  },
  "queue_depth": 0,
  "total_events_processed": 399
}